pymutation/__init__.py
pymutation/pymutation.py
pymutation-0.1.0.dist-info/METADATA
pymutation-0.1.0.dist-info/RECORD
pymutation-0.1.0.dist-info/WHEEL
pymutation-0.1.0.dist-info/top_level.txt
