Metadata-Version: 2.1
Name: pymutation
Version: 0.1.0
Summary: UNKNOWN
Home-page: https://github.com/kajchang/pymutation
Author: Kai Chang
Author-email: kaijchang@gmail.com
License: MIT
Platform: UNKNOWN
